streamlit_bokeh/__init__.py
streamlit_bokeh/pyproject.toml
streamlit_bokeh/frontend/build/index.html
streamlit_bokeh/frontend/build/assets/index-CksyyAp0.js
streamlit_bokeh/frontend/build/assets/index-DpEyMCkd.css
streamlit_bokeh/frontend/build/bokeh/LICENSE.txt
streamlit_bokeh/frontend/build/bokeh/bokeh-3.8.2.min.js
streamlit_bokeh/frontend/build/bokeh/bokeh-api-3.8.2.min.js
streamlit_bokeh/frontend/build/bokeh/bokeh-gl-3.8.2.min.js
streamlit_bokeh/frontend/build/bokeh/bokeh-mathjax-3.8.2.min.js
streamlit_bokeh/frontend/build/bokeh/bokeh-tables-3.8.2.min.js
streamlit_bokeh/frontend/build/bokeh/bokeh-widgets-3.8.2.min.js
streamlit_bokeh/frontend/build/fonts/Source-Sans-Pro.LICENSE
streamlit_bokeh/frontend/build/fonts/SourceSansPro-Bold.woff2
streamlit_bokeh/frontend/build/fonts/SourceSansPro-Regular.woff2
streamlit_bokeh/frontend/build/fonts/SourceSansPro-SemiBold.woff2
streamlit_bokeh/frontend/build/v2/index-DnwmlsBb.mjs
streamlit_bokeh-3.8.2.dist-info/licenses/LICENSE
streamlit_bokeh-3.8.2.dist-info/METADATA
streamlit_bokeh-3.8.2.dist-info/WHEEL
streamlit_bokeh-3.8.2.dist-info/top_level.txt
streamlit_bokeh-3.8.2.dist-info/RECORD
