Metadata-Version: 2.4
Name: streamlit-bokeh
Version: 3.8.2
Summary: Streamlit component that allows you to render Bokeh charts
Author-email: Snowflake Inc <hello@streamlit.io>
License-Expression: Apache-2.0
Project-URL: Homepage, https://streamlit.io
Project-URL: Source Code, https://github.com/streamlit/streamlit-bokeh
Project-URL: Bug Tracker, https://github.com/streamlit/streamlit/issues
Project-URL: Community, https://discuss.streamlit.io/
Project-URL: Twitter, https://twitter.com/streamlit
Classifier: Development Status :: 5 - Production/Stable
Classifier: Environment :: Console
Classifier: Environment :: Web Environment
Classifier: Intended Audience :: Developers
Classifier: Intended Audience :: Science/Research
Classifier: Programming Language :: Python :: 3.9
Classifier: Programming Language :: Python :: 3.10
Classifier: Programming Language :: Python :: 3.11
Classifier: Programming Language :: Python :: 3.12
Classifier: Programming Language :: Python :: 3.13
Classifier: Topic :: Scientific/Engineering :: Visualization
Requires-Python: >=3.9
License-File: LICENSE
Requires-Dist: streamlit>=1.26
Requires-Dist: bokeh==3.8.2
Provides-Extra: devel
Requires-Dist: wheel; extra == "devel"
Requires-Dist: pytest==7.4.0; extra == "devel"
Requires-Dist: playwright==1.48.0; extra == "devel"
Requires-Dist: requests==2.31.0; extra == "devel"
Requires-Dist: pytest-playwright-snapshot==1.0; extra == "devel"
Requires-Dist: pytest-rerunfailures==12.0; extra == "devel"
Dynamic: license-file
